[
  {
    "inputs": [
      {
        "internalType": "contract L2Vault",
        "name": "_vault",
        "type": "address"
      },
      {
        "internalType": "address",
        "name": "_acrossAddress",
        "type": "address"
      }
    ],
    "stateMutability": "nonpayable",
    "type": "constructor"
  },
  {
    "anonymous": false,
    "inputs": [
      {
        "indexed": false,
        "internalType": "uint256",
        "name": "assets",
        "type": "uint256"
      }
    ],
    "name": "TransferToVault",
    "type": "event"
  },
  {
    "stateMutability": "payable",
    "type": "fallback"
  },
  {
    "inputs": [],
    "name": "L1_CHAIN_ID",
    "outputs": [
      {
        "internalType": "uint256",
        "name": "",
        "type": "uint256"
      }
    ],
    "stateMutability": "view",
    "type": "function"
  },
  {
    "inputs": [],
    "name": "WETH",
    "outputs": [
      {
        "internalType": "contract WETH",
        "name": "",
        "type": "address"
      }
    ],
    "stateMutability": "view",
    "type": "function"
  },
  {
    "inputs": [],
    "name": "acrossBridge",
    "outputs": [
      {
        "internalType": "contract IAcrossBridge",
        "name": "",
        "type": "address"
      }
    ],
    "stateMutability": "view",
    "type": "function"
  },
  {
    "inputs": [],
    "name": "asset",
    "outputs": [
      {
        "internalType": "contract ERC20",
        "name": "",
        "type": "address"
      }
    ],
    "stateMutability": "view",
    "type": "function"
  },
  {
    "inputs": [
      {
        "internalType": "uint256",
        "name": "_amount",
        "type": "uint256"
      },
      {
        "internalType": "int64",
        "name": "_relayerFeePct",
        "type": "int64"
      }
    ],
    "name": "bridgeToL1",
    "outputs": [],
    "stateMutability": "nonpayable",
    "type": "function"
  },
  {
    "inputs": [
      {
        "internalType": "uint256",
        "name": "assets",
        "type": "uint256"
      },
      {
        "internalType": "bytes",
        "name": "exitProof",
        "type": "bytes"
      }
    ],
    "name": "clearFunds",
    "outputs": [],
    "stateMutability": "nonpayable",
    "type": "function"
  },
  {
    "inputs": [],
    "name": "governance",
    "outputs": [
      {
        "internalType": "address",
        "name": "",
        "type": "address"
      }
    ],
    "stateMutability": "view",
    "type": "function"
  },
  {
    "inputs": [],
    "name": "l1EscrowAddress",
    "outputs": [
      {
        "internalType": "address",
        "name": "",
        "type": "address"
      }
    ],
    "stateMutability": "view",
    "type": "function"
  },
  {
    "inputs": [
      {
        "internalType": "uint256",
        "name": "amount",
        "type": "uint256"
      },
      {
        "internalType": "bytes",
        "name": "exitProof",
        "type": "bytes"
      }
    ],
    "name": "rescueFunds",
    "outputs": [],
    "stateMutability": "nonpayable",
    "type": "function"
  },
  {
    "inputs": [
      {
        "internalType": "address",
        "name": "_acrossBridgeAddress",
        "type": "address"
      }
    ],
    "name": "setAcrossBridge",
    "outputs": [],
    "stateMutability": "nonpayable",
    "type": "function"
  },
  {
    "inputs": [
      {
        "internalType": "address",
        "name": "_l1EscrowAddress",
        "type": "address"
      }
    ],
    "name": "setL1Escrow",
    "outputs": [],
    "stateMutability": "nonpayable",
    "type": "function"
  },
  {
    "inputs": [],
    "name": "vault",
    "outputs": [
      {
        "internalType": "contract L2Vault",
        "name": "",
        "type": "address"
      }
    ],
    "stateMutability": "view",
    "type": "function"
  },
  {
    "inputs": [
      {
        "internalType": "uint256",
        "name": "_amount",
        "type": "uint256"
      }
    ],
    "name": "withdrawEth",
    "outputs": [],
    "stateMutability": "nonpayable",
    "type": "function"
  },
  {
    "inputs": [
      {
        "internalType": "address",
        "name": "_token",
        "type": "address"
      },
      {
        "internalType": "uint256",
        "name": "_amount",
        "type": "uint256"
      }
    ],
    "name": "withdrawToken",
    "outputs": [],
    "stateMutability": "nonpayable",
    "type": "function"
  },
  {
    "inputs": [],
    "name": "wormholeRouter",
    "outputs": [
      {
        "internalType": "address",
        "name": "",
        "type": "address"
      }
    ],
    "stateMutability": "view",
    "type": "function"
  },
  {
    "stateMutability": "payable",
    "type": "receive"
  }
]
